wrapper_b2p/__init__.py
wrapper_b2p/constant.py
wrapper_b2p/exception.py
wrapper_b2p/settings.py
wrapper_b2p/wrapper_class/__init__.py
wrapper_b2p/wrapper_class/authorize.py
wrapper_b2p/wrapper_class/authorize_by_token.py
wrapper_b2p/wrapper_class/authorize_inc.py
wrapper_b2p/wrapper_class/class_abs/__init__.py
wrapper_b2p/wrapper_class/class_abs/b2p_abc.py
wrapper_b2p/wrapper_class/class_abs/redirect_b2p_abc.py
wrapper_b2p/wrapper_class/class_abs/request_b2p_abc.py
wrapper_b2p/wrapper_class/complete.py
wrapper_b2p/wrapper_class/mixin/__init__.py
wrapper_b2p/wrapper_class/mixin/create_signature.py
wrapper_b2p/wrapper_class/mixin/get_url_stand_b2p.py
wrapper_b2p/wrapper_class/mixin/request_post_b2p.py
wrapper_b2p/wrapper_class/operation.py
wrapper_b2p/wrapper_class/order.py
wrapper_b2p/wrapper_class/purchase.py
wrapper_b2p/wrapper_class/purchase_by_token.py
wrapper_b2p/wrapper_class/register.py
wrapper_b2p/wrapper_class/reverse.py
wrapper_b2p-0.2.0.dist-info/LICENSE.rst
wrapper_b2p-0.2.0.dist-info/METADATA
wrapper_b2p-0.2.0.dist-info/WHEEL
wrapper_b2p-0.2.0.dist-info/RECORD
